{
  "alias": "app-mlperf-inference-reference",
  "automation_alias": "script",
  "automation_uid": "5b4e0237da074764",
  "deps": [
    {
      "tags": "set,echo-off,win"
    },
    {
      "tags": "detect,os,info"
    },
    {
      "tags": "detect,cpu,info"
    },
    {
      "tags": "get,sys-utils-cm"
    },
    {
      "names": [
        "python3"
      ],
      "tags": "get,python"
    },
    {
      "names": [
        "loadgen"
      ],
      "tags": "get,loadgen"
    },
    {
      "names": [
        "inference-src"
      ],
      "tags": "get,mlcommons,inference,src"
    },
    {
      "enable_if_env": {
        "CM_BACKEND": [
          "onnxruntime",
          "tvm-onnx"
        ]
      },
      "tags": "get,onnxruntime,python-lib"
    },
    {
      "enable_if_env": {
        "CM_BACKEND": [
          "tf",
          "tflite"
        ]
      },
      "tags": "get,tensorflow,python-lib"
    },
    {
      "enable_if_env": {
        "CM_MODEL": [
          "resnet50"
        ]
      },
      "names": [
        "imagenet-preprocessed"
      ],
      "tags": "get,dataset,image-classification,imagenet,preprocessed"
    },
    {
      "enable_if_env": {
        "CM_MODEL": [
          "resnet50"
        ]
      },
      "tags": "get,dataset-aux,image-classification,imagenet-aux"
    },
    {
      "enable_if_env": {
        "CM_MODEL": [
          "retinanet"
        ]
      },
      "tags": "get,dataset,object-detection,open-images,original"
    },
    {
      "enable_if_env": {
        "CM_MODEL": [
          "bert-99.9"
        ]
      },
      "tags": "get,dataset,squad,original"
    },
    {
      "enable_if_env": {
        "CM_MODEL": [
          "bert-99.9"
        ]
      },
      "tags": "get,transformers,python-lib"
    },
    {
      "enable_if_env": {
        "CM_MODEL": [
          "bert-99.9"
        ]
      },
      "tags": "get,tokenization,python-lib"
    },
    {
      "enable_if_env": {
        "CM_BACKEND": [
          "tf",
          "tflite"
        ],
        "CM_MODEL": [
          "resnet50"
        ]
      },
      "tags": "get,ml-model-tf,image-classification,resnet50"
    },
    {
      "enable_if_env": {
        "CM_BACKEND": [
          "pytorch"
        ],
        "CM_MODEL": [
          "resnet50"
        ]
      },
      "tags": "get,ml-model-pytorch,image-classification,resnet50"
    },
    {
      "enable_if_env": {
        "CM_BACKEND": [
          "onnxruntime",
          "tvm-onnx"
        ],
        "CM_MODEL": [
          "resnet50"
        ]
      },
      "tags": "get,ml-model-onnx,image-classification,resnet50"
    },
    {
      "enable_if_env": {
        "CM_BACKEND": [
          "onnxruntime"
        ],
        "CM_MODEL": [
          "bert-99.9"
        ]
      },
      "tags": "get,ml-model-onnx,language-processing,bert"
    },
    {
      "enable_if_env": {
        "CM_BACKEND": [
          "pytorch"
        ],
        "CM_MODEL": [
          "retinanet"
        ]
      },
      "tags": "get,ml-model,object-detection,resnext50,fp32,_pytorch"
    },
    {
      "enable_if_env": {
        "CM_BACKEND": [
          "onnxruntime"
        ],
        "CM_MODEL": [
          "retinanet"
        ]
      },
      "tags": "get,ml-model,object-detection,resnext50,fp32,_onnx"
    },
    {
      "enable_if_env": {
        "CM_DEVICE": [
          "gpu"
        ]
      },
      "tags": "get,cuda"
    },
    {
      "enable_if_env": {
        "CM_BACKEND": [
          "tf"
        ]
      },
      "names": [
        "tensorflow"
      ],
      "tags": "get,tensorflow"
    },
    {
      "enable_if_env": {
        "CM_BACKEND": [
          "tvm-onnx"
        ]
      },
      "names": [
        "tvm"
      ],
      "tags": "get,tvm,_llvm"
    },
    {
      "enable_if_env": {
        "CM_BACKEND": [
          "onnxruntime"
        ]
      },
      "tags": "get,pytorch"
    },
    {
      "enable_if_env": {
        "CM_BACKEND": [
          "pytorch"
        ]
      },
      "tags": "get,pytorch",
      "version": "1.8.0"
    },
    {
      "tags": "get,sut,configs"
    }
  ],
  "env": {
    "CM_BATCH_COUNT": "1",
    "CM_BATCH_SIZE": "1",
    "CM_OUTPUT_FOLDER_NAME": "test_results",
    "CM_RUN_STYLE": "test"
  },
  "input_mapping": {
    "count": "CM_LOADGEN_QUERY_COUNT",
    "docker": "CM_RUN_DOCKER_CONTAINER",
    "hw_name": "CM_HW_NAME",
    "imagenet_path": "IMAGENET_PATH",
    "max_batchsize": "CM_LOADGEN_MAX_BATCHSIZE",
    "mode": "CM_LOADGEN_MODE",
    "num_threads": "CM_NUM_THREADS",
    "output_dir": "OUTPUT_BASE_DIR",
    "power": "CM_SYSTEM_POWER",
    "rerun": "CM_RERUN",
    "scenario": "CM_LOADGEN_SCENARIO",
    "test_query_count": "CM_TEST_QUERY_COUNT"
  },
  "tags": [
    "app",
    "vision",
    "mlcommons",
    "mlperf",
    "inference",
    "reference",
    "ref",
    "python"
  ],
  "uid": "d775cac873ee4231",
  "variations": {
    "bert-99.9": {
      "env": {
        "CM_MODEL": "bert-99.9"
      },
      "post_deps": [
        {
          "enable_if_env": {
            "CM_LOADGEN_MODE": [
              "accuracy",
              "all"
            ],
            "CM_MLC_ACCURACY_RESULTS_DIR": [
              "on"
            ]
          },
          "names": [
            "accuracy-script"
          ],
          "tags": "run,accuracy,squad"
        }
      ]
    },
    "cpp": {
      "add_deps_recursive": {
        "accuracy-script": {
          "tags": "_int64"
        }
      },
      "env": {
        "CM_MLPERF_CPP": "yes"
      },
      "posthook_deps": [
        {
          "tags": "mlperf,cpp,vision,inference"
        }
      ]
    },
    "cpu": {
      "env": {
        "CM_DEVICE": "cpu"
      }
    },
    "fast": {
      "env": {
        "CM_FAST_FACTOR": "5",
        "CM_OUTPUT_FOLDER_NAME": "fast_results",
        "CM_RUN_STYLE": "fast"
      }
    },
    "gpu": {
      "env": {
        "CM_DEVICE": "gpu"
      }
    },
    "onnxruntime": {
      "add_deps_recursive": {
        "imagenet-preprocessed": {
          "tags": "_NCHW"
        }
      },
      "env": {
        "CM_BACKEND": "onnxruntime",
        "CM_BACKEND_VERSION": "<<<CM_ONNXRUNTIME_VERSION>>>"
      }
    },
    "pytorch": {
      "env": {
        "CM_BACKEND": "pytorch",
        "CM_BACKEND_VERSION": "<<<CM_PYTORCH_VERSION>>>"
      }
    },
    "r2.1_default": {
      "add_deps_recursive": {
        "compiler": {
          "tags": "llvm"
        },
        "inference-src": {
          "tags": "_octoml"
        },
        "loadgen": {
          "version": "r2.1"
        }
      },
      "env": {
        "CM_RERUN": "yes",
        "CM_SKIP_SYS_UTILS": "yes",
        "CM_TEST_QUERY_COUNT": "100"
      }
    },
    "resnet50": {
      "env": {
        "CM_MODEL": "resnet50"
      },
      "post_deps": [
        {
          "enable_if_env": {
            "CM_LOADGEN_MODE": [
              "accuracy",
              "all"
            ],
            "CM_MLC_ACCURACY_RESULTS_DIR": [
              "on"
            ]
          },
          "names": [
            "accuracy-script"
          ],
          "tags": "run,accuracy,imagenet"
        }
      ]
    },
    "retinanet": {
      "env": {
        "CM_MODEL": "retinanet"
      },
      "post_deps": [
        {
          "enable_if_env": {
            "CM_LOADGEN_MODE": [
              "accuracy",
              "all"
            ],
            "CM_MLC_ACCURACY_RESULTS_DIR": [
              "on"
            ]
          },
          "names": [
            "accuracy-script"
          ],
          "tags": "run,accuracy,openimages"
        }
      ]
    },
    "test": {
      "env": {
        "CM_OUTPUT_FOLDER_NAME": "test_results",
        "CM_RUN_STYLE": "test"
      }
    },
    "tf": {
      "add_deps_recursive": {
        "imagenet-preprocessed": {
          "tags": "_NHWC"
        }
      },
      "env": {
        "CM_BACKEND": "tf",
        "CM_BACKEND_VERSION": "<<<CM_TENSORFLOW_VERSION>>>"
      }
    },
    "tflite": {
      "env": {
        "CM_BACKEND": "tflite"
      }
    },
    "tvm-onnx": {
      "env": {
        "CM_BACKEND": "tvm-onnx",
        "CM_BACKEND_VERSION": "<<<CM_ONNXRUNTIME_VERSION>>>"
      }
    },
    "valid": {
      "env": {
        "CM_OUTPUT_FOLDER_NAME": "valid_results",
        "CM_RUN_STYLE": "valid"
      }
    }
  }
}
